lab_partner/__init__.py
lab_partner/config.py
lab_partner/docker.py
lab_partner/lab_control.py
lab_partner/process_utils.py
lab_partner/rootless.py
lab_partner/shell.py
lab_partner/types.py
lab_partner/user_info.py
lab_partner/compose_config/rootless/docker-compose-dev.yml
lab_partner/compose_config/rootless/docker-compose-init.yml
lab_partner/compose_config/rootless/docker-compose-rootless.yml
lab_partner/compose_config/shell/docker-compose.yml
lab_partner/docker_old/__init__.py
lab_partner/docker_old/daemon_info.py
lab_partner/docker_old/run_builder.py
lab_partner/tests/test_option_set.py
lab_partner/tests/docker/test_filters.py
lab_partner/tests/docker/test_rootless_container.py
lab_partner/tests/docker/test_run_builder.py
lab_partner-0.7.168.dist-info/LICENSE.md
lab_partner-0.7.168.dist-info/METADATA
lab_partner-0.7.168.dist-info/WHEEL
lab_partner-0.7.168.dist-info/entry_points.txt
lab_partner-0.7.168.dist-info/top_level.txt
lab_partner-0.7.168.dist-info/RECORD
