Metadata-Version: 2.1
Name: lab-partner
Version: 0.7.168
Summary: A toolkit that partners with you to build software projects
Author-email: Anthony Schexnaildre <aps@enclarify.com>
Maintainer-email: Anthony Schexnaildre <aps@enclarify.com>
License: # Released under MIT License
Project-URL: homepage, https://github.com/enclarify/lab-partner
Keywords: developer,tools,docker
Classifier: Programming Language :: Python :: 3
Classifier: License :: OSI Approved :: MIT License
Classifier: Operating System :: OS Independent
Classifier: Development Status :: 4 - Beta
Classifier: Intended Audience :: Developers
Classifier: Topic :: Software Development
Requires-Python: >=3.8
License-File: LICENSE.md
Requires-Dist: click==8.1.3
Provides-Extra: dev
Provides-Extra: test
Requires-Dist: pytest==8.1.1; extra == "test"
